{
    "_id":  "Xp5Iz6pm9Pao7o5w",
    "name":  "Canon Athenodorus",
    "type":  "npc",
    "img":  "modules/flee-mortals-custom/tokens/canon-athenodorus.webp",
    "system":  {
                   "abilities":  {
                                     "str":  {
                                                 "value":  20
                                             },
                                     "dex":  {
                                                 "value":  10
                                             },
                                     "con":  {
                                                 "value":  14
                                             },
                                     "int":  {
                                                 "value":  11
                                             },
                                     "wis":  {
                                                 "value":  20
                                             },
                                     "cha":  {
                                                 "value":  13
                                             }
                                 },
                   "attributes":  {
                                      "ac":  {
                                                 "flat":  18,
                                                 "calc":  "default",
                                                 "formula":  ""
                                             },
                                      "hp":  {
                                                 "value":  65,
                                                 "max":  65,
                                                 "temp":  0,
                                                 "tempmax":  0,
                                                 "formula":  "10d8 + 20"
                                             },
                                      "init":  {
                                                   "ability":  ""
                                               },
                                      "movement":  {
                                                       "walk":  30,
                                                       "fly":  0,
                                                       "swim":  0,
                                                       "climb":  0,
                                                       "burrow":  0,
                                                       "hover":  false,
                                                       "units":  "ft"
                                                   },
                                      "senses":  {
                                                     "darkvision":  0,
                                                     "blindsight":  0,
                                                     "tremorsense":  0,
                                                     "truesight":  0,
                                                     "units":  "ft",
                                                     "special":  ""
                                                 }
                                  },
                   "details":  {
                                   "cr":  3,
                                   "xp":  {
                                              "value":  700
                                          },
                                   "type":  {
                                                "value":  "humanoid",
                                                "subtype":  "Human",
                                                "custom":  ""
                                            },
                                   "alignment":  "Lawful Evil",
                                   "source":  {
                                                  "book":  "Flee, Mortals!"
                                              }
                               },
                   "traits":  {
                                  "size":  "med",
                                  "di":  {
                                             "value":  null
                                         },
                                  "dr":  {
                                             "value":  null
                                         },
                                  "dv":  {
                                             "value":  null
                                         },
                                  "ci":  {
                                             "value":  null
                                         },
                                  "languages":  {
                                                    "value":  "common",
                                                    "custom":  ""
                                                }
                              },
                   "skills":  {
                                  "rel":  {
                                              "value":  1
                                          },
                                  "dec":  {
                                              "value":  1
                                          },
                                  "ins":  {
                                              "value":  1
                                          },
                                  "ath":  {
                                              "value":  1
                                          }
                              }
               },
    "items":  [
                  {
                      "img":  "icons/svg/aura.svg",
                      "type":  "feat",
                      "system":  {
                                     "activation":  {
                                                        "type":  ""
                                                    },
                                     "description":  {
                                                         "value":  "\u003cp\u003eWhen Athenodorus makes an attack, he has advantage on the attack roll.\u003c/p\u003e"
                                                     },
                                     "source":  {
                                                    "book":  "Flee, Mortals!"
                                                },
                                     "type":  {
                                                  "value":  "monster",
                                                  "subtype":  ""
                                              }
                                 },
                      "name":  "Exploit Opening (3/Day)",
                      "_id":  "Epoc26K60hHMSKbt"
                  },
                  {
                      "img":  "icons/svg/sword.svg",
                      "type":  "weapon",
                      "system":  {
                                     "ability":  "str",
                                     "damage":  {
                                                    "parts":  [
                                                                  [
                                                                      "2d6 + 5",
                                                                      "bludgeoning"
                                                                  ]
                                                              ]
                                                },
                                     "source":  {
                                                    "book":  "Flee, Mortals!"
                                                },
                                     "description":  {
                                                         "value":  "\u003cp\u003eMelee Weapon Attack: +7 to hit, reach 10 ft., one target. Hit: 12 (2d6 + 5) bludgeoning damage. If the target is a creature, they are hexed until the end of their next turn. Whenever a creature hexed in this way makes an attack roll or saving throw, they must roll a d4 and subtract the number rolled from the attack roll or saving throw.\u003c/p\u003e"
                                                     },
                                     "target":  {
                                                    "value":  1,
                                                    "type":  "creature"
                                                },
                                     "attackBonus":  "7",
                                     "actionType":  "mwak",
                                     "range":  {
                                                   "units":  "ft",
                                                   "long":  null,
                                                   "value":  10
                                               }
                                 },
                      "name":  "Star of Iron",
                      "_id":  "KiQ7QOCKN0R5MALh"
                  },
                  {
                      "type":  "feat",
                      "img":  "icons/svg/book.svg",
                      "name":  "Iron Ring",
                      "system":  {
                                     "uses":  {
                                                  "recovery":  [

                                                               ],
                                                  "per":  "day",
                                                  "value":  2,
                                                  "max":  "2"
                                              },
                                     "activation":  {
                                                        "cost":  1,
                                                        "type":  "action"
                                                    },
                                     "description":  {
                                                         "value":  "\u003cp\u003eIf not in the Cyst, Athenodorus teleports to the Cyst. If in the Cyst, he teleports to a place he has visited.\u003c/p\u003e"
                                                     },
                                     "source":  {
                                                    "book":  "Flee, Mortals!"
                                                }
                                 },
                      "_id":  "cwSBZpvwBu6PphEN"
                  },
                  {
                      "img":  "icons/svg/book.svg",
                      "type":  "feat",
                      "system":  {
                                     "source":  {
                                                    "book":  "Flee, Mortals!"
                                                },
                                     "actionType":  "save",
                                     "description":  {
                                                         "value":  "\u003cp\u003eAthenodorus calls unholy black flames from the depths at a point he can see within 90 feet of him. Each enemy in a 15-foot-radius, 30-foot-high cylinder centered on that point must make a DC 15 Dexterity saving throw. On a failed save, a creature takes 14 (4d6) fire damage plus 14 (4d6) necrotic damage and is moved up to 15 feet horizontally. On a successful save, a creature takes half as much damage and isn\u0027t moved.\u003c/p\u003e"
                                                     },
                                     "uses":  {
                                                  "recovery":  [

                                                               ],
                                                  "per":  null,
                                                  "value":  null,
                                                  "max":  ""
                                              },
                                     "activation":  {
                                                        "cost":  1,
                                                        "type":  "action"
                                                    },
                                     "damage":  {
                                                    "parts":  [
                                                                  [
                                                                      "4d6",
                                                                      "fire"
                                                                  ]
                                                              ]
                                                },
                                     "save":  {
                                                  "dc":  15,
                                                  "ability":  "dex",
                                                  "scaling":  "flat"
                                              }
                                 },
                      "name":  "Unholy Fire (2/Day; 3rd-Level Spell)",
                      "_id":  "dfdhr7hzEXORqzZX"
                  },
                  {
                      "type":  "feat",
                      "img":  "icons/svg/wing.svg",
                      "name":  "Blessing of Ajax",
                      "system":  {
                                     "uses":  {
                                                  "recovery":  [

                                                               ],
                                                  "per":  "day",
                                                  "value":  2,
                                                  "max":  "2"
                                              },
                                     "activation":  {
                                                        "cost":  1,
                                                        "type":  "bonus"
                                                    },
                                     "description":  {
                                                         "value":  "\u003cp\u003eAthenodorus chooses a creature he can see within 30 feet of him. The target regains 14 (2d8 + 5) hit points and Athenodorus can end one of the following conditions affecting the target: blinded, charmed, dazed, deafened, frightened, paralyzed, poisoned, or stunned.\u003c/p\u003e"
                                                     },
                                     "source":  {
                                                    "book":  "Flee, Mortals!"
                                                }
                                 },
                      "_id":  "l6QkmG7OL2zI4MHe"
                  },
                  {
                      "type":  "feat",
                      "img":  "icons/svg/book.svg",
                      "name":  "Spellcasting (Utility)",
                      "system":  {
                                     "activation":  {
                                                        "type":  ""
                                                    },
                                     "description":  {
                                                         "value":  "\u003cp\u003eIn addition to any other spells in this stat block, Athenodorus can cast the following spells, using Wisdom as the spellcasting ability (spell save DC 15): At will: light, mending 1/day each: divination, glyph of warding\u003c/p\u003e"
                                                     },
                                     "source":  {
                                                    "book":  "Flee, Mortals!"
                                                },
                                     "type":  {
                                                  "value":  "monster",
                                                  "subtype":  ""
                                              }
                                 },
                      "_id":  "bnTDrEhGMeT0Wvlk"
                  }
              ],
    "effects":  [

                ],
    "prototypeToken":  {
                           "name":  "Canon Athenodorus",
                           "displayName":  20,
                           "actorLink":  false,
                           "texture":  {
                                           "src":  "modules/flee-mortals-custom/tokens/canon-athenodorus.webp",
                                           "scaleX":  1,
                                           "scaleY":  1
                                       },
                           "width":  1,
                           "height":  1,
                           "disposition":  -1,
                           "displayBars":  20,
                           "bar1":  {
                                        "attribute":  "attributes.hp"
                                    },
                           "sight":  {
                                         "enabled":  true,
                                         "range":  0
                                     }
                       },
    "flags":  {
                  "flee-mortals-custom":  {
                                              "role":  "Controller",
                                              "category":  "",
                                              "source":  "Flee, Mortals!"
                                          }
              }
}
