{
    "_id":  "iqs7ch52HQwzoYxh",
    "name":  "Essence of Mist",
    "type":  "npc",
    "img":  "modules/flee-mortals-custom/tokens/essence-of-mist.webp",
    "system":  {
                   "abilities":  {
                                     "str":  {
                                                 "value":  14
                                             },
                                     "dex":  {
                                                 "value":  20
                                             },
                                     "con":  {
                                                 "value":  17
                                             },
                                     "int":  {
                                                 "value":  12
                                             },
                                     "wis":  {
                                                 "value":  12
                                             },
                                     "cha":  {
                                                 "value":  16
                                             }
                                 },
                   "attributes":  {
                                      "ac":  {
                                                 "flat":  15,
                                                 "calc":  "natural",
                                                 "formula":  ""
                                             },
                                      "hp":  {
                                                 "value":  165,
                                                 "max":  165,
                                                 "temp":  0,
                                                 "tempmax":  0,
                                                 "formula":  "22d8 + 66"
                                             },
                                      "init":  {
                                                   "ability":  ""
                                               },
                                      "movement":  {
                                                       "walk":  40,
                                                       "fly":  20,
                                                       "swim":  0,
                                                       "climb":  0,
                                                       "burrow":  0,
                                                       "hover":  true,
                                                       "units":  "ft"
                                                   },
                                      "senses":  {
                                                     "darkvision":  120,
                                                     "blindsight":  60,
                                                     "tremorsense":  0,
                                                     "truesight":  0,
                                                     "units":  "ft",
                                                     "special":  ""
                                                 }
                                  },
                   "details":  {
                                   "cr":  13,
                                   "xp":  {
                                              "value":  10000
                                          },
                                   "type":  {
                                                "value":  "elemental",
                                                "subtype":  "Air, Water",
                                                "custom":  ""
                                            },
                                   "alignment":  "Any Alignment",
                                   "source":  {
                                                  "book":  "Flee, Mortals!"
                                              }
                               },
                   "traits":  {
                                  "size":  "med",
                                  "di":  {
                                             "value":  null
                                         },
                                  "dr":  {
                                             "value":  "psychic"
                                         },
                                  "dv":  {
                                             "value":  null
                                         },
                                  "ci":  {
                                             "value":  [
                                                           "blinded",
                                                           "charmed",
                                                           "frightened",
                                                           "grappled",
                                                           "prone",
                                                           "restrained"
                                                       ]
                                         },
                                  "languages":  {
                                                    "value":  [
                                                                  "aquan",
                                                                  "auran",
                                                                  "common"
                                                              ],
                                                    "custom":  ""
                                                }
                              },
                   "skills":  {
                                  "slt":  {
                                              "value":  1
                                          },
                                  "dec":  {
                                              "value":  1
                                          },
                                  "ste":  {
                                              "value":  1
                                          }
                              }
               },
    "items":  [
                  {
                      "img":  "icons/svg/aura.svg",
                      "type":  "feat",
                      "system":  {
                                     "activation":  {
                                                        "type":  ""
                                                    },
                                     "description":  {
                                                         "value":  "\u003cp\u003eThe essence can enter an enemy\u0027s space and stop there, and they can move through a space as narrow as 1 inch wide without squeezing.\u003c/p\u003e"
                                                     },
                                     "source":  {
                                                    "book":  "Flee, Mortals!"
                                                },
                                     "type":  {
                                                  "value":  "monster",
                                                  "subtype":  ""
                                              }
                                 },
                      "name":  "Flowing Form",
                      "_id":  "WSCXhoOtDsMKlUsc"
                  },
                  {
                      "img":  "icons/svg/aura.svg",
                      "type":  "feat",
                      "system":  {
                                     "activation":  {
                                                        "type":  ""
                                                    },
                                     "description":  {
                                                         "value":  "\u003cp\u003eWhile within 10 feet of the essence, creatures who need to breathe can\u0027t take reactions or speak.\u003c/p\u003e"
                                                     },
                                     "source":  {
                                                    "book":  "Flee, Mortals!"
                                                },
                                     "type":  {
                                                  "value":  "monster",
                                                  "subtype":  ""
                                              }
                                 },
                      "name":  "Gasping Aura",
                      "_id":  "QATpxYkeEnt6XmYi"
                  },
                  {
                      "img":  "icons/svg/book.svg",
                      "type":  "feat",
                      "system":  {
                                     "uses":  {
                                                  "recovery":  [

                                                               ],
                                                  "per":  null,
                                                  "value":  null,
                                                  "max":  ""
                                              },
                                     "activation":  {
                                                        "cost":  1,
                                                        "type":  "action"
                                                    },
                                     "description":  {
                                                         "value":  "\u003cp\u003eThe essence makes two Breathless Rend attacks.\u003c/p\u003e"
                                                     },
                                     "source":  {
                                                    "book":  "Flee, Mortals!"
                                                }
                                 },
                      "name":  "Multiattack",
                      "_id":  "IjOoVqVKdTHCPjMz"
                  },
                  {
                      "img":  "icons/svg/sword.svg",
                      "type":  "weapon",
                      "system":  {
                                     "ability":  "str",
                                     "damage":  {
                                                    "parts":  [
                                                                  [
                                                                      "2d8 + 5",
                                                                      "slashing"
                                                                  ],
                                                                  [
                                                                      "4d10",
                                                                      "psychic"
                                                                  ]
                                                              ]
                                                },
                                     "source":  {
                                                    "book":  "Flee, Mortals!"
                                                },
                                     "description":  {
                                                         "value":  "\u003cp\u003eMelee Weapon Attack: +10 to hit, reach 5 ft., one target. Hit: 14 (2d8 + 5) slashing damage plus 22 (4d10) psychic damage.\u003c/p\u003e"
                                                     },
                                     "target":  {
                                                    "value":  1,
                                                    "type":  "creature"
                                                },
                                     "attackBonus":  "10",
                                     "actionType":  "mwak",
                                     "range":  {
                                                   "units":  "ft",
                                                   "long":  null,
                                                   "value":  5
                                               }
                                 },
                      "name":  "Breathless Rend",
                      "_id":  "U9E2ZZvGXXjW1BFd"
                  },
                  {
                      "type":  "feat",
                      "img":  "icons/svg/wing.svg",
                      "name":  "Convocation of Breath",
                      "system":  {
                                     "source":  {
                                                    "book":  "Flee, Mortals!"
                                                },
                                     "actionType":  "save",
                                     "description":  {
                                                         "value":  "\u003cp\u003eThe essence imbues the power of breath in themself or another Elemental they can see within 30 feet of them, granting one of the following effects of that Elemental\u0027s choice:\n- Hide in Breath. The Elemental tries to hide inside the body of a creature within 10 feet of them who isn\u0027t a Construct, an Elemental, an Ooze, or an Undead. The target must succeed on a DC 18 Constitution saving throw or the Elemental retreats inside the target until the start of the Elemental\u0027s next turn. While inside the target, the Elemental can\u0027t take actions and has total cover against attacks and other effects outside the target.\n- Toxic Breath. The Elemental exudes a noxious aura 10 feet in every direction for 1 minute or until dispersed by a moderate or stronger wind. That area is lightly obscured, and each creature who needs to breathe who starts their turn in that area must succeed on a DC 16 Constitution saving throw or be poisoned until the end of their next turn.\u003c/p\u003e"
                                                     },
                                     "uses":  {
                                                  "recovery":  [

                                                               ],
                                                  "per":  "day",
                                                  "value":  2,
                                                  "max":  "2"
                                              },
                                     "activation":  {
                                                        "cost":  1,
                                                        "type":  "bonus"
                                                    },
                                     "save":  {
                                                  "dc":  18,
                                                  "ability":  "con",
                                                  "scaling":  "flat"
                                              }
                                 },
                      "_id":  "EfVtVmt3VROX0xkJ"
                  },
                  {
                      "type":  "feat",
                      "img":  "icons/svg/wing.svg",
                      "name":  "Breathstealer\u0027s Shimmer",
                      "system":  {
                                     "uses":  {
                                                  "recovery":  [

                                                               ],
                                                  "per":  "day",
                                                  "value":  1,
                                                  "max":  "1"
                                              },
                                     "activation":  {
                                                        "cost":  1,
                                                        "type":  "bonus"
                                                    },
                                     "description":  {
                                                         "value":  "\u003cp\u003eThe essence becomes invisible then takes the Hide action. This invisibility ends if the essence makes an attack or uses Convocation of Breath.\u003c/p\u003e"
                                                     },
                                     "source":  {
                                                    "book":  "Flee, Mortals!"
                                                }
                                 },
                      "_id":  "X1wKtbrseI21Hf6u"
                  }
              ],
    "effects":  [

                ],
    "prototypeToken":  {
                           "name":  "Essence of Mist",
                           "displayName":  20,
                           "actorLink":  false,
                           "texture":  {
                                           "src":  "modules/flee-mortals-custom/tokens/essence-of-mist.webp",
                                           "scaleX":  1,
                                           "scaleY":  1
                                       },
                           "width":  1,
                           "height":  1,
                           "disposition":  -1,
                           "displayBars":  20,
                           "bar1":  {
                                        "attribute":  "attributes.hp"
                                    },
                           "sight":  {
                                         "enabled":  true,
                                         "range":  0
                                     }
                       },
    "flags":  {
                  "flee-mortals-custom":  {
                                              "role":  "Ambusher",
                                              "category":  "",
                                              "source":  "Flee, Mortals!"
                                          }
              }
}
