{
    "_id":  "M8L9jNyCY09xYRpO",
    "name":  "Mycete",
    "type":  "npc",
    "img":  "modules/flee-mortals-custom/tokens/mycete.webp",
    "system":  {
                   "abilities":  {
                                     "str":  {
                                                 "value":  9
                                             },
                                     "dex":  {
                                                 "value":  12
                                             },
                                     "con":  {
                                                 "value":  14
                                             },
                                     "int":  {
                                                 "value":  10
                                             },
                                     "wis":  {
                                                 "value":  16
                                             },
                                     "cha":  {
                                                 "value":  12
                                             }
                                 },
                   "attributes":  {
                                      "ac":  {
                                                 "flat":  14,
                                                 "calc":  "default",
                                                 "formula":  ""
                                             },
                                      "hp":  {
                                                 "value":  26,
                                                 "max":  26,
                                                 "temp":  0,
                                                 "tempmax":  0,
                                                 "formula":  "4d8 + 8"
                                             },
                                      "init":  {
                                                   "ability":  ""
                                               },
                                      "movement":  {
                                                       "walk":  30,
                                                       "fly":  0,
                                                       "swim":  0,
                                                       "climb":  0,
                                                       "burrow":  0,
                                                       "hover":  false,
                                                       "units":  "ft"
                                                   },
                                      "senses":  {
                                                     "darkvision":  60,
                                                     "blindsight":  0,
                                                     "tremorsense":  0,
                                                     "truesight":  0,
                                                     "units":  "ft",
                                                     "special":  ""
                                                 }
                                  },
                   "details":  {
                                   "cr":  1,
                                   "xp":  {
                                              "value":  200
                                          },
                                   "type":  {
                                                "value":  "humanoid",
                                                "subtype":  "Tiefling",
                                                "custom":  ""
                                            },
                                   "alignment":  "Chaotic Evil",
                                   "source":  {
                                                  "book":  "Flee, Mortals!"
                                              }
                               },
                   "traits":  {
                                  "size":  "med",
                                  "di":  {
                                             "value":  "necrotic"
                                         },
                                  "dr":  {
                                             "value":  "fire"
                                         },
                                  "dv":  {
                                             "value":  null
                                         },
                                  "ci":  {
                                             "value":  null
                                         },
                                  "languages":  {
                                                    "value":  [
                                                                  "common",
                                                                  "infernal"
                                                              ],
                                                    "custom":  ""
                                                }
                              },
                   "skills":  {
                                  "nat":  {
                                              "value":  1
                                          },
                                  "per":  {
                                              "value":  1
                                          },
                                  "ins":  {
                                              "value":  1
                                          },
                                  "sur":  {
                                              "value":  1
                                          }
                              }
               },
    "items":  [
                  {
                      "img":  "icons/svg/aura.svg",
                      "type":  "feat",
                      "system":  {
                                     "activation":  {
                                                        "type":  ""
                                                    },
                                     "description":  {
                                                         "value":  "\u003cp\u003eWhenever Mycete is subjected to necrotic damage, she takes no damage and instead regains a number of hit points equal to the necrotic damage dealt.\u003c/p\u003e"
                                                     },
                                     "source":  {
                                                    "book":  "Flee, Mortals!"
                                                },
                                     "type":  {
                                                  "value":  "monster",
                                                  "subtype":  ""
                                              }
                                 },
                      "name":  "Necrotic Absorption",
                      "_id":  "tqihsd7k0hTyWFYA"
                  },
                  {
                      "type":  "feat",
                      "img":  "icons/svg/sword.svg",
                      "name":  "Parasitic Spores",
                      "system":  {
                                     "ability":  "",
                                     "damage":  {
                                                    "parts":  [
                                                                  [
                                                                      "2d6",
                                                                      "necrotic"
                                                                  ]
                                                              ]
                                                },
                                     "source":  {
                                                    "book":  "Flee, Mortals!"
                                                },
                                     "description":  {
                                                         "value":  "\u003cp\u003eMelee or Ranged Spell Attack: +5 to hit, reach 5 ft. or range 30 ft., one target. Hit: 7 (2d6) necrotic damage, and if the target is a creature, Mycete regains 3 (1d6) hit points.\u003c/p\u003e"
                                                     },
                                     "target":  {
                                                    "value":  1,
                                                    "type":  "creature"
                                                },
                                     "attackBonus":  "5",
                                     "actionType":  "rsak",
                                     "range":  {
                                                   "units":  "ft",
                                                   "long":  null,
                                                   "value":  30
                                               }
                                 },
                      "_id":  "auyo2WgRzJ01v8n1"
                  },
                  {
                      "img":  "icons/svg/book.svg",
                      "type":  "feat",
                      "system":  {
                                     "source":  {
                                                    "book":  "Flee, Mortals!"
                                                },
                                     "actionType":  "save",
                                     "description":  {
                                                         "value":  "\u003cp\u003eMycete causes fungi to proliferate from a point she can see within 60 feet of her. Solid surfaces in a 10-foot square centered on that point become difficult terrain, and a creature who enters that area for the first time on a turn or starts their turn there must succeed on a DC 13 Constitution saving throw or be poisoned for 1 minute (save ends at end of turn).\u003c/p\u003e"
                                                     },
                                     "uses":  {
                                                  "recovery":  [

                                                               ],
                                                  "per":  null,
                                                  "value":  null,
                                                  "max":  ""
                                              },
                                     "activation":  {
                                                        "cost":  1,
                                                        "type":  "action"
                                                    },
                                     "save":  {
                                                  "dc":  13,
                                                  "ability":  "con",
                                                  "scaling":  "flat"
                                              }
                                 },
                      "name":  "Fungal Growth",
                      "_id":  "UZROO9txpakemZum"
                  },
                  {
                      "type":  "feat",
                      "img":  "icons/svg/book.svg",
                      "name":  "Animate Husks",
                      "system":  {
                                     "uses":  {
                                                  "recovery":  [

                                                               ],
                                                  "per":  "day",
                                                  "value":  1,
                                                  "max":  "1"
                                              },
                                     "activation":  {
                                                        "cost":  1,
                                                        "type":  "action"
                                                    },
                                     "description":  {
                                                         "value":  "\u003cp\u003eMycete animates three rotting zombies, who appear in unoccupied spaces Mycete can see within 30 feet of her. The zombies act immediately after Mycete on the same initiative count and follow her verbal orders. If Mycete dies, the zombies are destroyed.\u003c/p\u003e"
                                                     },
                                     "source":  {
                                                    "book":  "Flee, Mortals!"
                                                }
                                 },
                      "_id":  "JGDQ3IolObjrcp8z"
                  },
                  {
                      "type":  "feat",
                      "img":  "icons/svg/wing.svg",
                      "name":  "Spore Eruption",
                      "system":  {
                                     "source":  {
                                                    "book":  "Flee, Mortals!"
                                                },
                                     "actionType":  "save",
                                     "description":  {
                                                         "value":  "\u003cp\u003eMycete destroys a rotting zombie under her control, and the zombie violently erupts with toxic spores. Each enemy within 5 feet of the zombie must make a DC 13 Constitution saving throw, taking 9 (2d8) necrotic damage on a failed save, or half as much damage on a successful one.\u003c/p\u003e"
                                                     },
                                     "uses":  {
                                                  "recovery":  [

                                                               ],
                                                  "per":  null,
                                                  "value":  null,
                                                  "max":  ""
                                              },
                                     "activation":  {
                                                        "cost":  1,
                                                        "type":  "bonus"
                                                    },
                                     "damage":  {
                                                    "parts":  [
                                                                  [
                                                                      "2d8",
                                                                      "necrotic"
                                                                  ]
                                                              ]
                                                },
                                     "save":  {
                                                  "dc":  13,
                                                  "ability":  "con",
                                                  "scaling":  "flat"
                                              }
                                 },
                      "_id":  "I1XQfhWtKf28iSVK"
                  },
                  {
                      "type":  "feat",
                      "img":  "icons/svg/book.svg",
                      "name":  "Spellcasting (Utility)",
                      "system":  {
                                     "activation":  {
                                                        "type":  ""
                                                    },
                                     "description":  {
                                                         "value":  "\u003cp\u003eIn addition to any other spells in this stat block, Mycete can cast the following spells, using Wisdom as the spellcasting ability (spell save DC 13): At will: druidcraft 3/day: locate animals or plants 1/day each: fog cloud, pass without trace\u003c/p\u003e"
                                                     },
                                     "source":  {
                                                    "book":  "Flee, Mortals!"
                                                },
                                     "type":  {
                                                  "value":  "monster",
                                                  "subtype":  ""
                                              }
                                 },
                      "_id":  "8aan9MnYFxspRCJx"
                  }
              ],
    "effects":  [

                ],
    "prototypeToken":  {
                           "name":  "Mycete",
                           "displayName":  20,
                           "actorLink":  false,
                           "texture":  {
                                           "src":  "modules/flee-mortals-custom/tokens/mycete.webp",
                                           "scaleX":  1,
                                           "scaleY":  1
                                       },
                           "width":  1,
                           "height":  1,
                           "disposition":  -1,
                           "displayBars":  20,
                           "bar1":  {
                                        "attribute":  "attributes.hp"
                                    },
                           "sight":  {
                                         "enabled":  true,
                                         "range":  0
                                     }
                       },
    "flags":  {
                  "flee-mortals-custom":  {
                                              "role":  "Controller",
                                              "category":  "",
                                              "source":  "Flee, Mortals!"
                                          }
              }
}
